{
    "annotations": [
        {
            "addressee": {
                "spans": [],
                "text": "",
                "tokenIds": []
            },
            "cue": {
                "spans": [
                    {
                        "begin": 17,
                        "charBegin": 108,
                        "charEnd": 112,
                        "end": 18
                    }
                ],
                "text": "laut",
                "tokenIds": [
                    17
                ]
            },
            "frame": {
                "spans": [
                    {
                        "begin": 17,
                        "charBegin": 108,
                        "charEnd": 124,
                        "end": 20
                    }
                ],
                "text": "laut den Angaben",
                "tokenIds": [
                    17,
                    18,
                    19
                ]
            },
            "hasNested": false,
            "id": 0,
            "isNested": false,
            "medium": "SW",
            "quote": {
                "spans": [
                    {
                        "begin": 0,
                        "charBegin": 0,
                        "charEnd": 107,
                        "end": 17
                    },
                    {
                        "begin": 20,
                        "charBegin": 125,
                        "charEnd": 167,
                        "end": 26
                    }
                ],
                "text": "Bei einem Busunfall am Freitagnachmittag im Colca-Tal, ein sehr beliebter Touristenort im Süden Perus, sind zwei deutsche Touristen ums Leben gekommen",
                "tokenIds": [
                    0,
                    1,
                    2,
                    3,
                    4,
                    5,
                    6,
                    7,
                    8,
                    9,
                    10,
                    11,
                    12,
                    13,
                    14,
                    15,
                    16,
                    20,
                    21,
                    22,
                    23,
                    24,
                    25
                ]
            },
            "speaker": {
                "spans": [
                    {
                        "begin": 18,
                        "charBegin": 113,
                        "charEnd": 124,
                        "end": 20
                    }
                ],
                "text": "den Angaben",
                "tokenIds": [
                    18,
                    19
                ]
            },
            "type": "Indirect"
        },
        {
            "addressee": {
                "spans": [],
                "text": "",
                "tokenIds": []
            },
            "cue": {
                "spans": [],
                "text": "",
                "tokenIds": []
            },
            "frame": {
                "spans": [],
                "text": "",
                "tokenIds": []
            },
            "hasNested": false,
            "id": 1,
            "isNested": false,
            "medium": "SW",
            "quote": {
                "spans": [
                    {
                        "begin": 35,
                        "charBegin": 226,
                        "charEnd": 288,
                        "end": 44
                    }
                ],
                "text": "die Verletzten seien zehn deutsche Touristen und zwei Peruaner",
                "tokenIds": [
                    35,
                    36,
                    37,
                    38,
                    39,
                    40,
                    41,
                    42,
                    43
                ]
            },
            "speaker": {
                "spans": [
                    {
                        "begin": 18,
                        "charBegin": 113,
                        "charEnd": 124,
                        "end": 20
                    }
                ],
                "text": "den Angaben",
                "tokenIds": [
                    18,
                    19
                ]
            },
            "type": "IndirectFreeIndirect"
        },
        {
            "addressee": {
                "spans": [],
                "text": "",
                "tokenIds": []
            },
            "cue": {
                "spans": [],
                "text": "",
                "tokenIds": []
            },
            "frame": {
                "spans": [],
                "text": "",
                "tokenIds": []
            },
            "hasNested": false,
            "id": 2,
            "isNested": false,
            "medium": "SW",
            "quote": {
                "spans": [
                    {
                        "begin": 45,
                        "charBegin": 290,
                        "charEnd": 484,
                        "end": 80
                    }
                ],
                "text": "Der Kleinbus sei auf dem Weg von Arequipa nach Chivay (ein Städtchen das etwa 3600 Meter über dem Meeresspiegel gelegen ist) vom Weg abgeraten und in einen 20 Meter tiefen Abgrund hinabgestürzt.",
                "tokenIds": [
                    45,
                    46,
                    47,
                    48,
                    49,
                    50,
                    51,
                    52,
                    53,
                    54,
                    55,
                    56,
                    57,
                    58,
                    59,
                    60,
                    61,
                    62,
                    63,
                    64,
                    65,
                    66,
                    67,
                    68,
                    69,
                    70,
                    71,
                    72,
                    73,
                    74,
                    75,
                    76,
                    77,
                    78,
                    79
                ]
            },
            "speaker": {
                "spans": [
                    {
                        "begin": 18,
                        "charBegin": 113,
                        "charEnd": 124,
                        "end": 20
                    }
                ],
                "text": "den Angaben",
                "tokenIds": [
                    18,
                    19
                ]
            },
            "type": "IndirectFreeIndirect"
        },
        {
            "addressee": {
                "spans": [],
                "text": "",
                "tokenIds": []
            },
            "cue": {
                "spans": [
                    {
                        "begin": 175,
                        "charBegin": 1021,
                        "charEnd": 1025,
                        "end": 176
                    }
                ],
                "text": "nach",
                "tokenIds": [
                    175
                ]
            },
            "frame": {
                "spans": [
                    {
                        "begin": 175,
                        "charBegin": 1021,
                        "charEnd": 1044,
                        "end": 178
                    }
                ],
                "text": "nach den Polizeiangaben",
                "tokenIds": [
                    175,
                    176,
                    177
                ]
            },
            "hasNested": false,
            "id": 3,
            "isNested": false,
            "medium": "SW",
            "quote": {
                "spans": [
                    {
                        "begin": 173,
                        "charBegin": 1010,
                        "charEnd": 1020,
                        "end": 175
                    },
                    {
                        "begin": 178,
                        "charBegin": 1045,
                        "charEnd": 1095,
                        "end": 186
                    }
                ],
                "text": "Dabei sind elf Personen gestorben und etwa 40 verletzt worden",
                "tokenIds": [
                    173,
                    174,
                    178,
                    179,
                    180,
                    181,
                    182,
                    183,
                    184,
                    185
                ]
            },
            "speaker": {
                "spans": [
                    {
                        "begin": 176,
                        "charBegin": 1026,
                        "charEnd": 1044,
                        "end": 178
                    }
                ],
                "text": "den Polizeiangaben",
                "tokenIds": [
                    176,
                    177
                ]
            },
            "type": "Indirect"
        }
    ],
    "documentName": "82396 - Busunfall im Colca-Tal: zwei deutsche Touristen ums Leben gekommen (2018-04-21)",
    "originalText": "Bei einem Busunfall am Freitagnachmittag im Colca-Tal, ein sehr beliebter Touristenort im Süden Perus, sind laut den Angaben zwei deutsche Touristen ums Leben gekommen. Zwölf andere Mitglieder der Reisegruppe wurden verletzt, die Verletzten seien zehn deutsche Touristen und zwei Peruaner. Der Kleinbus sei auf dem Weg von Arequipa nach Chivay (ein Städtchen das etwa 3600 Meter über dem Meeresspiegel gelegen ist) vom Weg abgeraten und in einen 20 Meter tiefen Abgrund hinabgestürzt. Die Verletzten wurden zum Krankenhaus in Arequipa gebracht.\n\nSehr bemerkenswert ist es, dass dies schon der dritte tödliche Busunfall in Peru innerhalb nur sehr kurzer Zeit ist. In derselben Gegend (Region Arequipa) geriet am Donnerstagabend ein Bus der auf dem Weg war von Chuquibamba nach Arequipa in einer Straßenkurve vom Weg ab und stürzte 60 Meter nach unten in einen Fluss, wobei sieben Personen starben und etwa 20 verletzt wurden. Außerdem stürzte in der Region La Libertad ein Bus in eine 200 Meter tiefe Schlucht. Dabei sind nach den Polizeiangaben elf Personen gestorben und etwa 40 verletzt worden.",
    "sentences": [
        {
            "begin": 0,
            "charBegin": 0,
            "charEnd": 168,
            "end": 27,
            "id": 0,
            "text": "Bei einem Busunfall am Freitagnachmittag im Colca-Tal, ein sehr beliebter Touristenort im Süden Perus, sind laut den Angaben zwei deutsche Touristen ums Leben gekommen. ",
            "tokenIds": [
                0,
                1,
                2,
                3,
                4,
                5,
                6,
                7,
                8,
                9,
                10,
                11,
                12,
                13,
                14,
                15,
                16,
                17,
                18,
                19,
                20,
                21,
                22,
                23,
                24,
                25,
                26
            ],
            "tokens": [
                "Bei",
                "einem",
                "Busunfall",
                "am",
                "Freitagnachmittag",
                "im",
                "Colca-Tal",
                ",",
                "ein",
                "sehr",
                "beliebter",
                "Touristenort",
                "im",
                "Süden",
                "Perus",
                ",",
                "sind",
                "laut",
                "den",
                "Angaben",
                "zwei",
                "deutsche",
                "Touristen",
                "ums",
                "Leben",
                "gekommen",
                "."
            ]
        },
        {
            "begin": 27,
            "charBegin": 169,
            "charEnd": 289,
            "end": 45,
            "id": 1,
            "text": "Zwölf andere Mitglieder der Reisegruppe wurden verletzt, die Verletzten seien zehn deutsche Touristen und zwei Peruaner. ",
            "tokenIds": [
                27,
                28,
                29,
                30,
                31,
                32,
                33,
                34,
                35,
                36,
                37,
                38,
                39,
                40,
                41,
                42,
                43,
                44
            ],
            "tokens": [
                "Zwölf",
                "andere",
                "Mitglieder",
                "der",
                "Reisegruppe",
                "wurden",
                "verletzt",
                ",",
                "die",
                "Verletzten",
                "seien",
                "zehn",
                "deutsche",
                "Touristen",
                "und",
                "zwei",
                "Peruaner",
                "."
            ]
        },
        {
            "begin": 45,
            "charBegin": 290,
            "charEnd": 484,
            "end": 80,
            "id": 2,
            "text": "Der Kleinbus sei auf dem Weg von Arequipa nach Chivay (ein Städtchen das etwa 3600 Meter über dem Meeresspiegel gelegen ist) vom Weg abgeraten und in einen 20 Meter tiefen Abgrund hinabgestürzt. ",
            "tokenIds": [
                45,
                46,
                47,
                48,
                49,
                50,
                51,
                52,
                53,
                54,
                55,
                56,
                57,
                58,
                59,
                60,
                61,
                62,
                63,
                64,
                65,
                66,
                67,
                68,
                69,
                70,
                71,
                72,
                73,
                74,
                75,
                76,
                77,
                78,
                79
            ],
            "tokens": [
                "Der",
                "Kleinbus",
                "sei",
                "auf",
                "dem",
                "Weg",
                "von",
                "Arequipa",
                "nach",
                "Chivay",
                "(",
                "ein",
                "Städtchen",
                "das",
                "etwa",
                "3600",
                "Meter",
                "über",
                "dem",
                "Meeresspiegel",
                "gelegen",
                "ist",
                ")",
                "vom",
                "Weg",
                "abgeraten",
                "und",
                "in",
                "einen",
                "20",
                "Meter",
                "tiefen",
                "Abgrund",
                "hinabgestürzt",
                "."
            ]
        },
        {
            "begin": 80,
            "charBegin": 485,
            "charEnd": 544,
            "end": 89,
            "id": 3,
            "text": "Die Verletzten wurden zum Krankenhaus in Arequipa gebracht.",
            "tokenIds": [
                80,
                81,
                82,
                83,
                84,
                85,
                86,
                87,
                88
            ],
            "tokens": [
                "Die",
                "Verletzten",
                "wurden",
                "zum",
                "Krankenhaus",
                "in",
                "Arequipa",
                "gebracht",
                "."
            ]
        },
        {
            "begin": 89,
            "charBegin": 546,
            "charEnd": 662,
            "end": 110,
            "id": 4,
            "text": "Sehr bemerkenswert ist es, dass dies schon der dritte tödliche Busunfall in Peru innerhalb nur sehr kurzer Zeit ist. ",
            "tokenIds": [
                89,
                90,
                91,
                92,
                93,
                94,
                95,
                96,
                97,
                98,
                99,
                100,
                101,
                102,
                103,
                104,
                105,
                106,
                107,
                108,
                109
            ],
            "tokens": [
                "Sehr",
                "bemerkenswert",
                "ist",
                "es",
                ",",
                "dass",
                "dies",
                "schon",
                "der",
                "dritte",
                "tödliche",
                "Busunfall",
                "in",
                "Peru",
                "innerhalb",
                "nur",
                "sehr",
                "kurzer",
                "Zeit",
                "ist",
                "."
            ]
        },
        {
            "begin": 110,
            "charBegin": 663,
            "charEnd": 924,
            "end": 157,
            "id": 5,
            "text": "In derselben Gegend (Region Arequipa) geriet am Donnerstagabend ein Bus der auf dem Weg war von Chuquibamba nach Arequipa in einer Straßenkurve vom Weg ab und stürzte 60 Meter nach unten in einen Fluss, wobei sieben Personen starben und etwa 20 verletzt wurden. ",
            "tokenIds": [
                110,
                111,
                112,
                113,
                114,
                115,
                116,
                117,
                118,
                119,
                120,
                121,
                122,
                123,
                124,
                125,
                126,
                127,
                128,
                129,
                130,
                131,
                132,
                133,
                134,
                135,
                136,
                137,
                138,
                139,
                140,
                141,
                142,
                143,
                144,
                145,
                146,
                147,
                148,
                149,
                150,
                151,
                152,
                153,
                154,
                155,
                156
            ],
            "tokens": [
                "In",
                "derselben",
                "Gegend",
                "(",
                "Region",
                "Arequipa",
                ")",
                "geriet",
                "am",
                "Donnerstagabend",
                "ein",
                "Bus",
                "der",
                "auf",
                "dem",
                "Weg",
                "war",
                "von",
                "Chuquibamba",
                "nach",
                "Arequipa",
                "in",
                "einer",
                "Straßenkurve",
                "vom",
                "Weg",
                "ab",
                "und",
                "stürzte",
                "60",
                "Meter",
                "nach",
                "unten",
                "in",
                "einen",
                "Fluss",
                ",",
                "wobei",
                "sieben",
                "Personen",
                "starben",
                "und",
                "etwa",
                "20",
                "verletzt",
                "wurden",
                "."
            ]
        },
        {
            "begin": 157,
            "charBegin": 925,
            "charEnd": 1009,
            "end": 173,
            "id": 6,
            "text": "Außerdem stürzte in der Region La Libertad ein Bus in eine 200 Meter tiefe Schlucht. ",
            "tokenIds": [
                157,
                158,
                159,
                160,
                161,
                162,
                163,
                164,
                165,
                166,
                167,
                168,
                169,
                170,
                171,
                172
            ],
            "tokens": [
                "Außerdem",
                "stürzte",
                "in",
                "der",
                "Region",
                "La",
                "Libertad",
                "ein",
                "Bus",
                "in",
                "eine",
                "200",
                "Meter",
                "tiefe",
                "Schlucht",
                "."
            ]
        },
        {
            "begin": 173,
            "charBegin": 1010,
            "charEnd": 1096,
            "end": 187,
            "id": 7,
            "text": "Dabei sind nach den Polizeiangaben elf Personen gestorben und etwa 40 verletzt worden.",
            "tokenIds": [
                173,
                174,
                175,
                176,
                177,
                178,
                179,
                180,
                181,
                182,
                183,
                184,
                185,
                186
            ],
            "tokens": [
                "Dabei",
                "sind",
                "nach",
                "den",
                "Polizeiangaben",
                "elf",
                "Personen",
                "gestorben",
                "und",
                "etwa",
                "40",
                "verletzt",
                "worden",
                "."
            ]
        }
    ],
    "tokens": [
        {
            "charBegin": 0,
            "charEnd": 3,
            "id": 0,
            "sentence": 1,
            "text": "Bei",
            "word": 1
        },
        {
            "charBegin": 4,
            "charEnd": 9,
            "id": 1,
            "sentence": 1,
            "text": "einem",
            "word": 2
        },
        {
            "charBegin": 10,
            "charEnd": 19,
            "id": 2,
            "sentence": 1,
            "text": "Busunfall",
            "word": 3
        },
        {
            "charBegin": 20,
            "charEnd": 22,
            "id": 3,
            "sentence": 1,
            "text": "am",
            "word": 4
        },
        {
            "charBegin": 23,
            "charEnd": 40,
            "id": 4,
            "sentence": 1,
            "text": "Freitagnachmittag",
            "word": 5
        },
        {
            "charBegin": 41,
            "charEnd": 43,
            "id": 5,
            "sentence": 1,
            "text": "im",
            "word": 6
        },
        {
            "charBegin": 44,
            "charEnd": 53,
            "id": 6,
            "sentence": 1,
            "text": "Colca-Tal",
            "word": 7
        },
        {
            "charBegin": 53,
            "charEnd": 54,
            "id": 7,
            "sentence": 1,
            "text": ",",
            "word": 8
        },
        {
            "charBegin": 55,
            "charEnd": 58,
            "id": 8,
            "sentence": 1,
            "text": "ein",
            "word": 9
        },
        {
            "charBegin": 59,
            "charEnd": 63,
            "id": 9,
            "sentence": 1,
            "text": "sehr",
            "word": 10
        },
        {
            "charBegin": 64,
            "charEnd": 73,
            "id": 10,
            "sentence": 1,
            "text": "beliebter",
            "word": 11
        },
        {
            "charBegin": 74,
            "charEnd": 86,
            "id": 11,
            "sentence": 1,
            "text": "Touristenort",
            "word": 12
        },
        {
            "charBegin": 87,
            "charEnd": 89,
            "id": 12,
            "sentence": 1,
            "text": "im",
            "word": 13
        },
        {
            "charBegin": 90,
            "charEnd": 95,
            "id": 13,
            "sentence": 1,
            "text": "Süden",
            "word": 14
        },
        {
            "charBegin": 96,
            "charEnd": 101,
            "id": 14,
            "sentence": 1,
            "text": "Perus",
            "word": 15
        },
        {
            "charBegin": 101,
            "charEnd": 102,
            "id": 15,
            "sentence": 1,
            "text": ",",
            "word": 16
        },
        {
            "charBegin": 103,
            "charEnd": 107,
            "id": 16,
            "sentence": 1,
            "text": "sind",
            "word": 17
        },
        {
            "charBegin": 108,
            "charEnd": 112,
            "id": 17,
            "sentence": 1,
            "text": "laut",
            "word": 18
        },
        {
            "charBegin": 113,
            "charEnd": 116,
            "id": 18,
            "sentence": 1,
            "text": "den",
            "word": 19
        },
        {
            "charBegin": 117,
            "charEnd": 124,
            "id": 19,
            "sentence": 1,
            "text": "Angaben",
            "word": 20
        },
        {
            "charBegin": 125,
            "charEnd": 129,
            "id": 20,
            "sentence": 1,
            "text": "zwei",
            "word": 21
        },
        {
            "charBegin": 130,
            "charEnd": 138,
            "id": 21,
            "sentence": 1,
            "text": "deutsche",
            "word": 22
        },
        {
            "charBegin": 139,
            "charEnd": 148,
            "id": 22,
            "sentence": 1,
            "text": "Touristen",
            "word": 23
        },
        {
            "charBegin": 149,
            "charEnd": 152,
            "id": 23,
            "sentence": 1,
            "text": "ums",
            "word": 24
        },
        {
            "charBegin": 153,
            "charEnd": 158,
            "id": 24,
            "sentence": 1,
            "text": "Leben",
            "word": 25
        },
        {
            "charBegin": 159,
            "charEnd": 167,
            "id": 25,
            "sentence": 1,
            "text": "gekommen",
            "word": 26
        },
        {
            "charBegin": 167,
            "charEnd": 168,
            "id": 26,
            "sentence": 1,
            "text": ".",
            "word": 27
        },
        {
            "charBegin": 169,
            "charEnd": 174,
            "id": 27,
            "sentence": 2,
            "text": "Zwölf",
            "word": 1
        },
        {
            "charBegin": 175,
            "charEnd": 181,
            "id": 28,
            "sentence": 2,
            "text": "andere",
            "word": 2
        },
        {
            "charBegin": 182,
            "charEnd": 192,
            "id": 29,
            "sentence": 2,
            "text": "Mitglieder",
            "word": 3
        },
        {
            "charBegin": 193,
            "charEnd": 196,
            "id": 30,
            "sentence": 2,
            "text": "der",
            "word": 4
        },
        {
            "charBegin": 197,
            "charEnd": 208,
            "id": 31,
            "sentence": 2,
            "text": "Reisegruppe",
            "word": 5
        },
        {
            "charBegin": 209,
            "charEnd": 215,
            "id": 32,
            "sentence": 2,
            "text": "wurden",
            "word": 6
        },
        {
            "charBegin": 216,
            "charEnd": 224,
            "id": 33,
            "sentence": 2,
            "text": "verletzt",
            "word": 7
        },
        {
            "charBegin": 224,
            "charEnd": 225,
            "id": 34,
            "sentence": 2,
            "text": ",",
            "word": 8
        },
        {
            "charBegin": 226,
            "charEnd": 229,
            "id": 35,
            "sentence": 2,
            "text": "die",
            "word": 9
        },
        {
            "charBegin": 230,
            "charEnd": 240,
            "id": 36,
            "sentence": 2,
            "text": "Verletzten",
            "word": 10
        },
        {
            "charBegin": 241,
            "charEnd": 246,
            "id": 37,
            "sentence": 2,
            "text": "seien",
            "word": 11
        },
        {
            "charBegin": 247,
            "charEnd": 251,
            "id": 38,
            "sentence": 2,
            "text": "zehn",
            "word": 12
        },
        {
            "charBegin": 252,
            "charEnd": 260,
            "id": 39,
            "sentence": 2,
            "text": "deutsche",
            "word": 13
        },
        {
            "charBegin": 261,
            "charEnd": 270,
            "id": 40,
            "sentence": 2,
            "text": "Touristen",
            "word": 14
        },
        {
            "charBegin": 271,
            "charEnd": 274,
            "id": 41,
            "sentence": 2,
            "text": "und",
            "word": 15
        },
        {
            "charBegin": 275,
            "charEnd": 279,
            "id": 42,
            "sentence": 2,
            "text": "zwei",
            "word": 16
        },
        {
            "charBegin": 280,
            "charEnd": 288,
            "id": 43,
            "sentence": 2,
            "text": "Peruaner",
            "word": 17
        },
        {
            "charBegin": 288,
            "charEnd": 289,
            "id": 44,
            "sentence": 2,
            "text": ".",
            "word": 18
        },
        {
            "charBegin": 290,
            "charEnd": 293,
            "id": 45,
            "sentence": 3,
            "text": "Der",
            "word": 1
        },
        {
            "charBegin": 294,
            "charEnd": 302,
            "id": 46,
            "sentence": 3,
            "text": "Kleinbus",
            "word": 2
        },
        {
            "charBegin": 303,
            "charEnd": 306,
            "id": 47,
            "sentence": 3,
            "text": "sei",
            "word": 3
        },
        {
            "charBegin": 307,
            "charEnd": 310,
            "id": 48,
            "sentence": 3,
            "text": "auf",
            "word": 4
        },
        {
            "charBegin": 311,
            "charEnd": 314,
            "id": 49,
            "sentence": 3,
            "text": "dem",
            "word": 5
        },
        {
            "charBegin": 315,
            "charEnd": 318,
            "id": 50,
            "sentence": 3,
            "text": "Weg",
            "word": 6
        },
        {
            "charBegin": 319,
            "charEnd": 322,
            "id": 51,
            "sentence": 3,
            "text": "von",
            "word": 7
        },
        {
            "charBegin": 323,
            "charEnd": 331,
            "id": 52,
            "sentence": 3,
            "text": "Arequipa",
            "word": 8
        },
        {
            "charBegin": 332,
            "charEnd": 336,
            "id": 53,
            "sentence": 3,
            "text": "nach",
            "word": 9
        },
        {
            "charBegin": 337,
            "charEnd": 343,
            "id": 54,
            "sentence": 3,
            "text": "Chivay",
            "word": 10
        },
        {
            "charBegin": 344,
            "charEnd": 345,
            "id": 55,
            "sentence": 3,
            "text": "(",
            "word": 11
        },
        {
            "charBegin": 345,
            "charEnd": 348,
            "id": 56,
            "sentence": 3,
            "text": "ein",
            "word": 12
        },
        {
            "charBegin": 349,
            "charEnd": 358,
            "id": 57,
            "sentence": 3,
            "text": "Städtchen",
            "word": 13
        },
        {
            "charBegin": 359,
            "charEnd": 362,
            "id": 58,
            "sentence": 3,
            "text": "das",
            "word": 14
        },
        {
            "charBegin": 363,
            "charEnd": 367,
            "id": 59,
            "sentence": 3,
            "text": "etwa",
            "word": 15
        },
        {
            "charBegin": 368,
            "charEnd": 372,
            "id": 60,
            "sentence": 3,
            "text": "3600",
            "word": 16
        },
        {
            "charBegin": 373,
            "charEnd": 378,
            "id": 61,
            "sentence": 3,
            "text": "Meter",
            "word": 17
        },
        {
            "charBegin": 379,
            "charEnd": 383,
            "id": 62,
            "sentence": 3,
            "text": "über",
            "word": 18
        },
        {
            "charBegin": 384,
            "charEnd": 387,
            "id": 63,
            "sentence": 3,
            "text": "dem",
            "word": 19
        },
        {
            "charBegin": 388,
            "charEnd": 401,
            "id": 64,
            "sentence": 3,
            "text": "Meeresspiegel",
            "word": 20
        },
        {
            "charBegin": 402,
            "charEnd": 409,
            "id": 65,
            "sentence": 3,
            "text": "gelegen",
            "word": 21
        },
        {
            "charBegin": 410,
            "charEnd": 413,
            "id": 66,
            "sentence": 3,
            "text": "ist",
            "word": 22
        },
        {
            "charBegin": 413,
            "charEnd": 414,
            "id": 67,
            "sentence": 3,
            "text": ")",
            "word": 23
        },
        {
            "charBegin": 415,
            "charEnd": 418,
            "id": 68,
            "sentence": 3,
            "text": "vom",
            "word": 24
        },
        {
            "charBegin": 419,
            "charEnd": 422,
            "id": 69,
            "sentence": 3,
            "text": "Weg",
            "word": 25
        },
        {
            "charBegin": 423,
            "charEnd": 432,
            "id": 70,
            "sentence": 3,
            "text": "abgeraten",
            "word": 26
        },
        {
            "charBegin": 433,
            "charEnd": 436,
            "id": 71,
            "sentence": 3,
            "text": "und",
            "word": 27
        },
        {
            "charBegin": 437,
            "charEnd": 439,
            "id": 72,
            "sentence": 3,
            "text": "in",
            "word": 28
        },
        {
            "charBegin": 440,
            "charEnd": 445,
            "id": 73,
            "sentence": 3,
            "text": "einen",
            "word": 29
        },
        {
            "charBegin": 446,
            "charEnd": 448,
            "id": 74,
            "sentence": 3,
            "text": "20",
            "word": 30
        },
        {
            "charBegin": 449,
            "charEnd": 454,
            "id": 75,
            "sentence": 3,
            "text": "Meter",
            "word": 31
        },
        {
            "charBegin": 455,
            "charEnd": 461,
            "id": 76,
            "sentence": 3,
            "text": "tiefen",
            "word": 32
        },
        {
            "charBegin": 462,
            "charEnd": 469,
            "id": 77,
            "sentence": 3,
            "text": "Abgrund",
            "word": 33
        },
        {
            "charBegin": 470,
            "charEnd": 483,
            "id": 78,
            "sentence": 3,
            "text": "hinabgestürzt",
            "word": 34
        },
        {
            "charBegin": 483,
            "charEnd": 484,
            "id": 79,
            "sentence": 3,
            "text": ".",
            "word": 35
        },
        {
            "charBegin": 485,
            "charEnd": 488,
            "id": 80,
            "sentence": 4,
            "text": "Die",
            "word": 1
        },
        {
            "charBegin": 489,
            "charEnd": 499,
            "id": 81,
            "sentence": 4,
            "text": "Verletzten",
            "word": 2
        },
        {
            "charBegin": 500,
            "charEnd": 506,
            "id": 82,
            "sentence": 4,
            "text": "wurden",
            "word": 3
        },
        {
            "charBegin": 507,
            "charEnd": 510,
            "id": 83,
            "sentence": 4,
            "text": "zum",
            "word": 4
        },
        {
            "charBegin": 511,
            "charEnd": 522,
            "id": 84,
            "sentence": 4,
            "text": "Krankenhaus",
            "word": 5
        },
        {
            "charBegin": 523,
            "charEnd": 525,
            "id": 85,
            "sentence": 4,
            "text": "in",
            "word": 6
        },
        {
            "charBegin": 526,
            "charEnd": 534,
            "id": 86,
            "sentence": 4,
            "text": "Arequipa",
            "word": 7
        },
        {
            "charBegin": 535,
            "charEnd": 543,
            "id": 87,
            "sentence": 4,
            "text": "gebracht",
            "word": 8
        },
        {
            "charBegin": 543,
            "charEnd": 544,
            "id": 88,
            "sentence": 4,
            "text": ".",
            "word": 9
        },
        {
            "charBegin": 546,
            "charEnd": 550,
            "id": 89,
            "sentence": 5,
            "text": "Sehr",
            "word": 1
        },
        {
            "charBegin": 551,
            "charEnd": 564,
            "id": 90,
            "sentence": 5,
            "text": "bemerkenswert",
            "word": 2
        },
        {
            "charBegin": 565,
            "charEnd": 568,
            "id": 91,
            "sentence": 5,
            "text": "ist",
            "word": 3
        },
        {
            "charBegin": 569,
            "charEnd": 571,
            "id": 92,
            "sentence": 5,
            "text": "es",
            "word": 4
        },
        {
            "charBegin": 571,
            "charEnd": 572,
            "id": 93,
            "sentence": 5,
            "text": ",",
            "word": 5
        },
        {
            "charBegin": 573,
            "charEnd": 577,
            "id": 94,
            "sentence": 5,
            "text": "dass",
            "word": 6
        },
        {
            "charBegin": 578,
            "charEnd": 582,
            "id": 95,
            "sentence": 5,
            "text": "dies",
            "word": 7
        },
        {
            "charBegin": 583,
            "charEnd": 588,
            "id": 96,
            "sentence": 5,
            "text": "schon",
            "word": 8
        },
        {
            "charBegin": 589,
            "charEnd": 592,
            "id": 97,
            "sentence": 5,
            "text": "der",
            "word": 9
        },
        {
            "charBegin": 593,
            "charEnd": 599,
            "id": 98,
            "sentence": 5,
            "text": "dritte",
            "word": 10
        },
        {
            "charBegin": 600,
            "charEnd": 608,
            "id": 99,
            "sentence": 5,
            "text": "tödliche",
            "word": 11
        },
        {
            "charBegin": 609,
            "charEnd": 618,
            "id": 100,
            "sentence": 5,
            "text": "Busunfall",
            "word": 12
        },
        {
            "charBegin": 619,
            "charEnd": 621,
            "id": 101,
            "sentence": 5,
            "text": "in",
            "word": 13
        },
        {
            "charBegin": 622,
            "charEnd": 626,
            "id": 102,
            "sentence": 5,
            "text": "Peru",
            "word": 14
        },
        {
            "charBegin": 627,
            "charEnd": 636,
            "id": 103,
            "sentence": 5,
            "text": "innerhalb",
            "word": 15
        },
        {
            "charBegin": 637,
            "charEnd": 640,
            "id": 104,
            "sentence": 5,
            "text": "nur",
            "word": 16
        },
        {
            "charBegin": 641,
            "charEnd": 645,
            "id": 105,
            "sentence": 5,
            "text": "sehr",
            "word": 17
        },
        {
            "charBegin": 646,
            "charEnd": 652,
            "id": 106,
            "sentence": 5,
            "text": "kurzer",
            "word": 18
        },
        {
            "charBegin": 653,
            "charEnd": 657,
            "id": 107,
            "sentence": 5,
            "text": "Zeit",
            "word": 19
        },
        {
            "charBegin": 658,
            "charEnd": 661,
            "id": 108,
            "sentence": 5,
            "text": "ist",
            "word": 20
        },
        {
            "charBegin": 661,
            "charEnd": 662,
            "id": 109,
            "sentence": 5,
            "text": ".",
            "word": 21
        },
        {
            "charBegin": 663,
            "charEnd": 665,
            "id": 110,
            "sentence": 6,
            "text": "In",
            "word": 1
        },
        {
            "charBegin": 666,
            "charEnd": 675,
            "id": 111,
            "sentence": 6,
            "text": "derselben",
            "word": 2
        },
        {
            "charBegin": 676,
            "charEnd": 682,
            "id": 112,
            "sentence": 6,
            "text": "Gegend",
            "word": 3
        },
        {
            "charBegin": 683,
            "charEnd": 684,
            "id": 113,
            "sentence": 6,
            "text": "(",
            "word": 4
        },
        {
            "charBegin": 684,
            "charEnd": 690,
            "id": 114,
            "sentence": 6,
            "text": "Region",
            "word": 5
        },
        {
            "charBegin": 691,
            "charEnd": 699,
            "id": 115,
            "sentence": 6,
            "text": "Arequipa",
            "word": 6
        },
        {
            "charBegin": 699,
            "charEnd": 700,
            "id": 116,
            "sentence": 6,
            "text": ")",
            "word": 7
        },
        {
            "charBegin": 701,
            "charEnd": 707,
            "id": 117,
            "sentence": 6,
            "text": "geriet",
            "word": 8
        },
        {
            "charBegin": 708,
            "charEnd": 710,
            "id": 118,
            "sentence": 6,
            "text": "am",
            "word": 9
        },
        {
            "charBegin": 711,
            "charEnd": 726,
            "id": 119,
            "sentence": 6,
            "text": "Donnerstagabend",
            "word": 10
        },
        {
            "charBegin": 727,
            "charEnd": 730,
            "id": 120,
            "sentence": 6,
            "text": "ein",
            "word": 11
        },
        {
            "charBegin": 731,
            "charEnd": 734,
            "id": 121,
            "sentence": 6,
            "text": "Bus",
            "word": 12
        },
        {
            "charBegin": 735,
            "charEnd": 738,
            "id": 122,
            "sentence": 6,
            "text": "der",
            "word": 13
        },
        {
            "charBegin": 739,
            "charEnd": 742,
            "id": 123,
            "sentence": 6,
            "text": "auf",
            "word": 14
        },
        {
            "charBegin": 743,
            "charEnd": 746,
            "id": 124,
            "sentence": 6,
            "text": "dem",
            "word": 15
        },
        {
            "charBegin": 747,
            "charEnd": 750,
            "id": 125,
            "sentence": 6,
            "text": "Weg",
            "word": 16
        },
        {
            "charBegin": 751,
            "charEnd": 754,
            "id": 126,
            "sentence": 6,
            "text": "war",
            "word": 17
        },
        {
            "charBegin": 755,
            "charEnd": 758,
            "id": 127,
            "sentence": 6,
            "text": "von",
            "word": 18
        },
        {
            "charBegin": 759,
            "charEnd": 770,
            "id": 128,
            "sentence": 6,
            "text": "Chuquibamba",
            "word": 19
        },
        {
            "charBegin": 771,
            "charEnd": 775,
            "id": 129,
            "sentence": 6,
            "text": "nach",
            "word": 20
        },
        {
            "charBegin": 776,
            "charEnd": 784,
            "id": 130,
            "sentence": 6,
            "text": "Arequipa",
            "word": 21
        },
        {
            "charBegin": 785,
            "charEnd": 787,
            "id": 131,
            "sentence": 6,
            "text": "in",
            "word": 22
        },
        {
            "charBegin": 788,
            "charEnd": 793,
            "id": 132,
            "sentence": 6,
            "text": "einer",
            "word": 23
        },
        {
            "charBegin": 794,
            "charEnd": 806,
            "id": 133,
            "sentence": 6,
            "text": "Straßenkurve",
            "word": 24
        },
        {
            "charBegin": 807,
            "charEnd": 810,
            "id": 134,
            "sentence": 6,
            "text": "vom",
            "word": 25
        },
        {
            "charBegin": 811,
            "charEnd": 814,
            "id": 135,
            "sentence": 6,
            "text": "Weg",
            "word": 26
        },
        {
            "charBegin": 815,
            "charEnd": 817,
            "id": 136,
            "sentence": 6,
            "text": "ab",
            "word": 27
        },
        {
            "charBegin": 818,
            "charEnd": 821,
            "id": 137,
            "sentence": 6,
            "text": "und",
            "word": 28
        },
        {
            "charBegin": 822,
            "charEnd": 829,
            "id": 138,
            "sentence": 6,
            "text": "stürzte",
            "word": 29
        },
        {
            "charBegin": 830,
            "charEnd": 832,
            "id": 139,
            "sentence": 6,
            "text": "60",
            "word": 30
        },
        {
            "charBegin": 833,
            "charEnd": 838,
            "id": 140,
            "sentence": 6,
            "text": "Meter",
            "word": 31
        },
        {
            "charBegin": 839,
            "charEnd": 843,
            "id": 141,
            "sentence": 6,
            "text": "nach",
            "word": 32
        },
        {
            "charBegin": 844,
            "charEnd": 849,
            "id": 142,
            "sentence": 6,
            "text": "unten",
            "word": 33
        },
        {
            "charBegin": 850,
            "charEnd": 852,
            "id": 143,
            "sentence": 6,
            "text": "in",
            "word": 34
        },
        {
            "charBegin": 853,
            "charEnd": 858,
            "id": 144,
            "sentence": 6,
            "text": "einen",
            "word": 35
        },
        {
            "charBegin": 859,
            "charEnd": 864,
            "id": 145,
            "sentence": 6,
            "text": "Fluss",
            "word": 36
        },
        {
            "charBegin": 864,
            "charEnd": 865,
            "id": 146,
            "sentence": 6,
            "text": ",",
            "word": 37
        },
        {
            "charBegin": 866,
            "charEnd": 871,
            "id": 147,
            "sentence": 6,
            "text": "wobei",
            "word": 38
        },
        {
            "charBegin": 872,
            "charEnd": 878,
            "id": 148,
            "sentence": 6,
            "text": "sieben",
            "word": 39
        },
        {
            "charBegin": 879,
            "charEnd": 887,
            "id": 149,
            "sentence": 6,
            "text": "Personen",
            "word": 40
        },
        {
            "charBegin": 888,
            "charEnd": 895,
            "id": 150,
            "sentence": 6,
            "text": "starben",
            "word": 41
        },
        {
            "charBegin": 896,
            "charEnd": 899,
            "id": 151,
            "sentence": 6,
            "text": "und",
            "word": 42
        },
        {
            "charBegin": 900,
            "charEnd": 904,
            "id": 152,
            "sentence": 6,
            "text": "etwa",
            "word": 43
        },
        {
            "charBegin": 905,
            "charEnd": 907,
            "id": 153,
            "sentence": 6,
            "text": "20",
            "word": 44
        },
        {
            "charBegin": 908,
            "charEnd": 916,
            "id": 154,
            "sentence": 6,
            "text": "verletzt",
            "word": 45
        },
        {
            "charBegin": 917,
            "charEnd": 923,
            "id": 155,
            "sentence": 6,
            "text": "wurden",
            "word": 46
        },
        {
            "charBegin": 923,
            "charEnd": 924,
            "id": 156,
            "sentence": 6,
            "text": ".",
            "word": 47
        },
        {
            "charBegin": 925,
            "charEnd": 933,
            "id": 157,
            "sentence": 7,
            "text": "Außerdem",
            "word": 1
        },
        {
            "charBegin": 934,
            "charEnd": 941,
            "id": 158,
            "sentence": 7,
            "text": "stürzte",
            "word": 2
        },
        {
            "charBegin": 942,
            "charEnd": 944,
            "id": 159,
            "sentence": 7,
            "text": "in",
            "word": 3
        },
        {
            "charBegin": 945,
            "charEnd": 948,
            "id": 160,
            "sentence": 7,
            "text": "der",
            "word": 4
        },
        {
            "charBegin": 949,
            "charEnd": 955,
            "id": 161,
            "sentence": 7,
            "text": "Region",
            "word": 5
        },
        {
            "charBegin": 956,
            "charEnd": 958,
            "id": 162,
            "sentence": 7,
            "text": "La",
            "word": 6
        },
        {
            "charBegin": 959,
            "charEnd": 967,
            "id": 163,
            "sentence": 7,
            "text": "Libertad",
            "word": 7
        },
        {
            "charBegin": 968,
            "charEnd": 971,
            "id": 164,
            "sentence": 7,
            "text": "ein",
            "word": 8
        },
        {
            "charBegin": 972,
            "charEnd": 975,
            "id": 165,
            "sentence": 7,
            "text": "Bus",
            "word": 9
        },
        {
            "charBegin": 976,
            "charEnd": 978,
            "id": 166,
            "sentence": 7,
            "text": "in",
            "word": 10
        },
        {
            "charBegin": 979,
            "charEnd": 983,
            "id": 167,
            "sentence": 7,
            "text": "eine",
            "word": 11
        },
        {
            "charBegin": 984,
            "charEnd": 987,
            "id": 168,
            "sentence": 7,
            "text": "200",
            "word": 12
        },
        {
            "charBegin": 988,
            "charEnd": 993,
            "id": 169,
            "sentence": 7,
            "text": "Meter",
            "word": 13
        },
        {
            "charBegin": 994,
            "charEnd": 999,
            "id": 170,
            "sentence": 7,
            "text": "tiefe",
            "word": 14
        },
        {
            "charBegin": 1000,
            "charEnd": 1008,
            "id": 171,
            "sentence": 7,
            "text": "Schlucht",
            "word": 15
        },
        {
            "charBegin": 1008,
            "charEnd": 1009,
            "id": 172,
            "sentence": 7,
            "text": ".",
            "word": 16
        },
        {
            "charBegin": 1010,
            "charEnd": 1015,
            "id": 173,
            "sentence": 8,
            "text": "Dabei",
            "word": 1
        },
        {
            "charBegin": 1016,
            "charEnd": 1020,
            "id": 174,
            "sentence": 8,
            "text": "sind",
            "word": 2
        },
        {
            "charBegin": 1021,
            "charEnd": 1025,
            "id": 175,
            "sentence": 8,
            "text": "nach",
            "word": 3
        },
        {
            "charBegin": 1026,
            "charEnd": 1029,
            "id": 176,
            "sentence": 8,
            "text": "den",
            "word": 4
        },
        {
            "charBegin": 1030,
            "charEnd": 1044,
            "id": 177,
            "sentence": 8,
            "text": "Polizeiangaben",
            "word": 5
        },
        {
            "charBegin": 1045,
            "charEnd": 1048,
            "id": 178,
            "sentence": 8,
            "text": "elf",
            "word": 6
        },
        {
            "charBegin": 1049,
            "charEnd": 1057,
            "id": 179,
            "sentence": 8,
            "text": "Personen",
            "word": 7
        },
        {
            "charBegin": 1058,
            "charEnd": 1067,
            "id": 180,
            "sentence": 8,
            "text": "gestorben",
            "word": 8
        },
        {
            "charBegin": 1068,
            "charEnd": 1071,
            "id": 181,
            "sentence": 8,
            "text": "und",
            "word": 9
        },
        {
            "charBegin": 1072,
            "charEnd": 1076,
            "id": 182,
            "sentence": 8,
            "text": "etwa",
            "word": 10
        },
        {
            "charBegin": 1077,
            "charEnd": 1079,
            "id": 183,
            "sentence": 8,
            "text": "40",
            "word": 11
        },
        {
            "charBegin": 1080,
            "charEnd": 1088,
            "id": 184,
            "sentence": 8,
            "text": "verletzt",
            "word": 12
        },
        {
            "charBegin": 1089,
            "charEnd": 1095,
            "id": 185,
            "sentence": 8,
            "text": "worden",
            "word": 13
        },
        {
            "charBegin": 1095,
            "charEnd": 1096,
            "id": 186,
            "sentence": 8,
            "text": ".",
            "word": 14
        }
    ]
}